logpilot/log.py
logpilot-0.2.1.dist-info/LICENSE
logpilot-0.2.1.dist-info/METADATA
logpilot-0.2.1.dist-info/WHEEL
logpilot-0.2.1.dist-info/top_level.txt
logpilot-0.2.1.dist-info/RECORD
